[{"steamid":76561198941654798,"heroID":85,"kills":21,"items":["item_gladiator_guard","item_ultimate_boots","item_ghost","item_blade_midas","item_refresher_core","item_manaback","item_eternal_shroud","","","","","","","","","item_dezun_bloodrite"]},
{"steamid":76561199148772004,"heroID":137,"kills":5,"items":["item_boots_of_bearing","item_travel_boots","item_trident_custom","item_blade_midas","item_phase_boots","item_shivas_strom","","","","","","","","","","item_gunpowder_gauntlets"]},
{"steamid":76561198192808195,"heroID":33,"kills":10,"items":["item_radiance_prc","item_magic_crit","","item_ultimate_scepter","","","","","","","","","","","",""]},
{"steamid":76561198184278654,"heroID":155,"kills":4,"items":["","","","","","","","","","","","","","","",""]},
{"steamid":76561199253370979,"heroID":1,"kills":35,"items":["item_manta","item_devostator","item_nullifier","item_basher_slardar","item_ghost","item_ultimate_orb","","","","","","","","","","item_mana_draught"]},
{"steamid":76561199143899907,"heroID":39,"kills":15,"items":["item_blade_midas","item_hurricane_lens","item_trident_custom","item_refresher_core","item_great_magic_crit","item_ward_dispenser","","","","item_ogre_axe","","","","","","item_poor_mans_shield"]}]